setup.py
xcal3d/__init__.py
xcal3d/dumpskel.py
xcal3d/filteranim.py
xcal3d/filtermesh.py
xcal3d/makejson.py
xcal3d/makepickle.py
xcal3d/makeurdf.py
xcal3d/showbodyinfo.py
xcal3d/testload.py
xcal3d.egg-info/PKG-INFO
xcal3d.egg-info/SOURCES.txt
xcal3d.egg-info/dependency_links.txt
xcal3d.egg-info/makejson.py
xcal3d.egg-info/top_level.txt