Metadata-Version: 1.1
Name: xcal3d
Version: 0.2.0
Summary: A package to load and manipulate Virtual Human CAL3D files directly in  Python
Home-page: https://github.com/eruffaldi/pyxcal3d
Author: Emanuele Ruffaldi
Author-email: emanuele.ruffaldi@gmail.com
License: BSD
Keywords: cal3d avatar
Platform: UNKNOWN
Classifier: Development Status :: 3 - Alpha
Classifier: Topic :: Utilities
Classifier: License :: OSI Approved :: BSD License
